dio_processador_imagens/__init__.py
dio_processador_imagens/processamento/__init__.py
dio_processador_imagens/processamento/combinacao.py
dio_processador_imagens/processamento/transformacao.py
dio_processador_imagens/utils/__init__.py
dio_processador_imagens/utils/io.py
dio_processador_imagens/utils/plot.py
dio_processador_imagens-0.0.2.dist-info/METADATA
dio_processador_imagens-0.0.2.dist-info/WHEEL
dio_processador_imagens-0.0.2.dist-info/top_level.txt
dio_processador_imagens-0.0.2.dist-info/RECORD
