Metadata-Version: 2.1
Name: dio-processador-imagens
Version: 0.0.2
Summary: Pacote simples de processamento de imagens
Home-page: https://github.com/agnerlana/descomplicando_processamento_imagens.git
Author: Agner_Lana
Requires-Python: >=3.5
Requires-Dist: matplotlib
Requires-Dist: numpy
Requires-Dist: scikit-image (>=0.18.0)
